LICENSE
README.md
setup.py
DependencyParser/DependencyRelation.py
DependencyParser/ParserEvaluationScore.py
DependencyParser/__init__.py
DependencyParser/Stanford/StanfordDependencyRelation.py
DependencyParser/Stanford/StanfordDependencyType.py
DependencyParser/Stanford/__init__.py
DependencyParser/Turkish/TurkishDependencyRelation.py
DependencyParser/Turkish/TurkishDependencyTreeBankCorpus.py
DependencyParser/Turkish/TurkishDependencyTreeBankSentence.py
DependencyParser/Turkish/TurkishDependencyTreeBankWord.py
DependencyParser/Turkish/TurkishDependencyType.py
DependencyParser/Turkish/__init__.py
DependencyParser/Universal/UniversalDependencyPosType.py
DependencyParser/Universal/UniversalDependencyRelation.py
DependencyParser/Universal/UniversalDependencyTreeBankCorpus.py
DependencyParser/Universal/UniversalDependencyTreeBankFeatures.py
DependencyParser/Universal/UniversalDependencyTreeBankSentence.py
DependencyParser/Universal/UniversalDependencyTreeBankWord.py
DependencyParser/Universal/UniversalDependencyType.py
DependencyParser/Universal/__init__.py
NlpToolkit_DependencyParser.egg-info/PKG-INFO
NlpToolkit_DependencyParser.egg-info/SOURCES.txt
NlpToolkit_DependencyParser.egg-info/dependency_links.txt
NlpToolkit_DependencyParser.egg-info/requires.txt
NlpToolkit_DependencyParser.egg-info/top_level.txt