Metadata-Version: 2.1
Name: NlpToolkit-DependencyParser
Version: 1.0.24
Summary: Turkish Dependency Parser
Home-page: https://github.com/StarlangSoftware/TurkishDependencyParser-Py
Author: olcaytaner
Author-email: olcay.yildiz@ozyegin.edu.tr
License: UNKNOWN
Platform: UNKNOWN
